{
  "project_info": {
    "project_number": "834052870681",
    "project_id": "my-portfolio-c56e8",
    "storage_bucket": "my-portfolio-c56e8.firebasestorage.app"
  },
  "client": [
    {
      "client_info": {
        "mobilesdk_app_id": "1:834052870681:android:dc758c4a02ded40c27d088",
        "android_client_info": {
          "package_name": "com.example.my_prtofolio"
        }
      },
      "oauth_client": [],
      "api_key": [
        {
          "current_key": "AIzaSyA7Vp9WYt9nt0ZTWgHhSp_FcrSRZ_ja79g"
        }
      ],
      "services": {
        "appinvite_service": {
          "other_platform_oauth_client": []
        }
      }
    }
  ],
  "configuration_version": "1"
}